gitbundle/_config/config_test.yaml
gitbundle/branch/CurrentBranchResolver.py
gitbundle/containerInit.py
gitbundle/GitBundle.py
gitbundle/GitBundleTest.py
gitbundle/repository/CurrentRepositoryFactory.py
git_bundle-0.1.0b1.dist-info/LICENSE
git_bundle-0.1.0b1.dist-info/WHEEL
git_bundle-0.1.0b1.dist-info/METADATA
git_bundle-0.1.0b1.dist-info/RECORD
