Metadata-Version: 2.1
Name: git-bundle
Version: 0.1.0b1
Summary: Provides GIT focused parameters and classes
Home-page: https://github.com/pyfony/git-bundle
License: MIT
Author: Jiri Koutny
Author-email: jiri.koutny@datasentics.com
Requires-Python: >=3.7.3,<3.8.0
Classifier: License :: OSI Approved :: MIT License
Classifier: Operating System :: OS Independent
Classifier: Programming Language :: Python :: 3
Requires-Dist: pyfony-bundles (>=0.2.0,<0.3.0)
Requires-Dist: pygit2 (>=0.28.0,<0.29.0)
Project-URL: Repository, https://github.com/pyfony/git-bundle
